admin_timeline/__init__.py
admin_timeline/compat.py
admin_timeline/conf.py
admin_timeline/defaults.py
admin_timeline/forms.py
admin_timeline/models.py
admin_timeline/settings.py
admin_timeline/urls.py
admin_timeline/views.py
admin_timeline/static/admin_timeline/css/admin_timeline.css
admin_timeline/static/admin_timeline/images/loading.gif
admin_timeline/static/admin_timeline/js/admin_timeline.js
admin_timeline/static/admin_timeline/libs/jquery-1.11.2.min.js
admin_timeline/static/admin_timeline/libs/multiple-select/jquery.multiple.select.js
admin_timeline/static/admin_timeline/libs/multiple-select/multiple-select.css
admin_timeline/static/admin_timeline/libs/multiple-select/multiple-select.png
admin_timeline/templates/admin_timeline/timeline.html
admin_timeline/templates/admin_timeline/timeline_ajax.html
admin_timeline/templates/admin_timeline/django_lte14/timeline.html
admin_timeline/templates/admin_timeline/django_lte14/timeline_ajax.html
admin_timeline/templatetags/__init__.py
admin_timeline/templatetags/admin_timeline_tags.py
admin_timeline/tests/__init__.py
admin_timeline/tests/base.py
admin_timeline/tests/data.py
admin_timeline/tests/helpers.py
admin_timeline/tests/test_core.py
django_admin_timeline-1.8.dist-info/LICENSE_GPL2.0.txt
django_admin_timeline-1.8.dist-info/LICENSE_LGPL_2.1.txt
django_admin_timeline-1.8.dist-info/METADATA
django_admin_timeline-1.8.dist-info/WHEEL
django_admin_timeline-1.8.dist-info/top_level.txt
django_admin_timeline-1.8.dist-info/RECORD
