Metadata-Version: 2.1
Name: django-admin-timeline
Version: 1.8
Summary: Facebook-like timeline for Django admin
Home-page: https://github.com/barseghyanartur/django-admin-timeline
Author: Artur Barseghyan
Author-email: artur.barseghyan@gmail.com
License: GPL-2.0-only OR LGPL-2.1-or-later
Keywords: django-admin-timeline,django,app,python
Platform: UNKNOWN
Classifier: Programming Language :: Python
Classifier: Programming Language :: Python :: 3
Classifier: Programming Language :: Python :: 3.6
Classifier: Programming Language :: Python :: 3.7
Classifier: Programming Language :: Python :: 3.8
Classifier: Environment :: Web Environment
Classifier: Framework :: Django
Classifier: Intended Audience :: Developers
Classifier: Operating System :: OS Independent
Classifier: Development Status :: 5 - Production/Stable
Classifier: License :: OSI Approved :: GNU General Public License v2 (GPLv2)
Classifier: License :: OSI Approved :: GNU Lesser General Public License v2 or later (LGPLv2+)
Requires-Dist: six (>=1.7.3)
Requires-Dist: django-nine (>=0.1.10)
